app.py
main.py
scrape.py
words.py
werdl_chat-0.0.2.dist-info/METADATA
werdl_chat-0.0.2.dist-info/WHEEL
werdl_chat-0.0.2.dist-info/licenses/LICENSE
werdl_chat-0.0.2.dist-info/RECORD
